LICENSE
MANIFEST.in
README.md
requirements.txt
setup.py
sajjad_tester.egg-info/PKG-INFO
sajjad_tester.egg-info/SOURCES.txt
sajjad_tester.egg-info/dependency_links.txt
sajjad_tester.egg-info/requires.txt
sajjad_tester.egg-info/top_level.txt
test/__init__.py
test/test_main.py
xworker/__init__.py
xworker/main.py
xworker/utils.py
xworker/templates/base.html
xworker/templates/index.html
xworker/web/__init__.py